mopidy_qobuz/__init__.py
mopidy_qobuz/backend.py
mopidy_qobuz/browse.py
mopidy_qobuz/ext.conf
mopidy_qobuz/library.py
mopidy_qobuz/lookup.py
mopidy_qobuz/playback.py
mopidy_qobuz/playlists.py
mopidy_qobuz/search.py
mopidy_qobuz/translator.py
Mopidy_Qobuz-0.0.1.dist-info/LICENSE
Mopidy_Qobuz-0.0.1.dist-info/METADATA
Mopidy_Qobuz-0.0.1.dist-info/WHEEL
Mopidy_Qobuz-0.0.1.dist-info/entry_points.txt
Mopidy_Qobuz-0.0.1.dist-info/top_level.txt
Mopidy_Qobuz-0.0.1.dist-info/RECORD
