Metadata-Version: 2.1
Name: Mopidy-Qobuz
Version: 0.0.1
Summary: Mopidy extension for playing music from Qobuz
Home-page: https://github.com/taschenb/mopidy-qobuz
Author: taschenb
Author-email: taschenb@posteo.de
License: Apache License, Version 2.0
Platform: UNKNOWN
Classifier: Environment :: No Input/Output (Daemon)
Classifier: Intended Audience :: End Users/Desktop
Classifier: License :: OSI Approved :: Apache Software License
Classifier: Operating System :: OS Independent
Classifier: Programming Language :: Python :: 2
Classifier: Topic :: Multimedia :: Sound/Audio :: Players
Requires-Dist: Mopidy (>=2.0)
Requires-Dist: Pykka (>=1.1)
Requires-Dist: qobuz (>=0.0.1)
Requires-Dist: setuptools
